README.txt
setup.py
src/zc/__init__.py
src/zc.metarecipe.egg-info/PKG-INFO
src/zc.metarecipe.egg-info/SOURCES.txt
src/zc.metarecipe.egg-info/dependency_links.txt
src/zc.metarecipe.egg-info/entry_points.txt
src/zc.metarecipe.egg-info/namespace_packages.txt
src/zc.metarecipe.egg-info/not-zip-safe
src/zc.metarecipe.egg-info/requires.txt
src/zc.metarecipe.egg-info/top_level.txt
src/zc/metarecipe/README.txt
src/zc/metarecipe/__init__.py
src/zc/metarecipe/testing.py
src/zc/metarecipe/tests.py